neelthee_mansion/Books.py
neelthee_mansion/Mansion_of_Amnesia.py
neelthee_mansion/Quests.py
neelthee_mansion/Rooms.py
neelthee_mansion/__init__.py
neelthee_mansion/__main__.py
neelthee_mansion/all_game_utils.py
neelthee_mansion/creatures.py
neelthee_mansion/items.py
neelthee_mansion/utils.py
neelthee_mansion-3.24.13.dist-info/LICENSE.md
neelthee_mansion-3.24.13.dist-info/METADATA
neelthee_mansion-3.24.13.dist-info/WHEEL
neelthee_mansion-3.24.13.dist-info/entry_points.txt
neelthee_mansion-3.24.13.dist-info/top_level.txt
neelthee_mansion-3.24.13.dist-info/RECORD
