Metadata-Version: 2.2
Name: neelthee_mansion
Version: 3.24.13
Summary: A text-based adventure game set in Neel-thee’s mansion.
Home-page: https://github.com/Flameblade375/neelthee_mansion
Author: Alexander.E.F
Author-email: alexander@xandy.rocks
License: MIT
Classifier: Programming Language :: Python :: 3
Classifier: Programming Language :: Python :: 3.6
Classifier: Programming Language :: Python :: 3.7
Classifier: Programming Language :: Python :: 3.8
Classifier: Programming Language :: Python :: 3.9
Classifier: Programming Language :: Python :: 3.10
Classifier: Programming Language :: Python :: 3.11
Classifier: License :: OSI Approved :: MIT License
Classifier: Operating System :: OS Independent
Requires-Python: >=3.6
License-File: LICENSE.md
Requires-Dist: wheel
Requires-Dist: psutil
Requires-Dist: playsound
Requires-Dist: requests
Requires-Dist: keyboard
Requires-Dist: pandas
Requires-Dist: validators
Requires-Dist: dicttoxml
Requires-Dist: pytz
Dynamic: author
Dynamic: author-email
Dynamic: classifier
Dynamic: description
Dynamic: description-content-type
Dynamic: home-page
Dynamic: license
Dynamic: requires-dist
Dynamic: requires-python
Dynamic: summary
